add_header.py
demo.py
interactive_demo.py
braidpy/__init__.py
braidpy/artin_generators.py
braidpy/braid.py
braidpy/braid_catalog.py
braidpy/braidword.py
braidpy/garside_canonical_form.py
braidpy/handles_reduction.py
braidpy/material_braid.py
braidpy/operations.py
braidpy/ordered_strands.py
braidpy/parametric_braid.py
braidpy/parametric_strand.py
braidpy/properties.py
braidpy/pure_braid.py
braidpy/utils.py
braidpy-0.2.2.dist-info/licenses/LICENSE
braidpy-0.2.2.dist-info/METADATA
braidpy-0.2.2.dist-info/WHEEL
braidpy-0.2.2.dist-info/top_level.txt
braidpy-0.2.2.dist-info/RECORD
