Metadata-Version: 2.4
Name: braidpy
Version: 0.2.2
Summary: Python library for working with braids
Author-email: Baptiste Labat <baptiste.labat@gmail.com>
License: MPL-2.0
Classifier: Development Status :: 3 - Alpha
Classifier: Intended Audience :: Developers
Classifier: Intended Audience :: Science/Research
Classifier: License :: OSI Approved :: Mozilla Public License 2.0 (MPL 2.0)
Classifier: Programming Language :: Python :: 3
Classifier: Programming Language :: Python :: 3.8
Classifier: Programming Language :: Python :: 3.9
Classifier: Programming Language :: Python :: 3.10
Classifier: Programming Language :: Python :: 3.11
Classifier: Topic :: Scientific/Engineering :: Mathematics
Requires-Python: <4.0,>=3.10
License-File: LICENSE
Requires-Dist: braidvisualiser>=0.2.2
Requires-Dist: matplotlib>=3.7.5
Requires-Dist: numpy>=1.21.0
Requires-Dist: pyqt6>=6.9.0
Requires-Dist: sympy>=1.14.0
Requires-Dist: tornado>=6.4.2
Requires-Dist: math-braid<0.9,>=0.8
Requires-Dist: plotly>=6.1.2
Dynamic: license-file
